<?xml version="1.0" encoding="UTF-8"?><retConsReciNFe xmlns="http://www.portalfiscal.inf.br/nfe" versao="1.10"><tpAmb>2</tpAmb><verAplic>SP_NFE_PL_005e</verAplic><nRec>350000017872062</nRec><cStat>104</cStat><xMotivo>Lote processado</xMotivo><cUF>35</cUF><protNFe versao="1.10"><infProt><tpAmb>2</tpAmb><verAplic>SP_NFE_PL_005e</verAplic><chNFe>35100708982270000157550010000002055816354680</chNFe><dhRecbto>2010-07-20T12:53:02</dhRecbto><nProt>135100023420032</nProt><digVal>ILOOOlStYi1Szhe7G3N9B/y7JBY=</digVal><cStat>100</cStat><xMotivo>Autorizado o uso da NF-e</xMotivo></infProt></protNFe></retConsReciNFe>
